pymmcore_nano-11.10.0.74.0.dist-info/RECORD
pymmcore_nano-11.10.0.74.0.dist-info/WHEEL
pymmcore_nano-11.10.0.74.0.dist-info/METADATA
pymmcore_nano/__init__.py
pymmcore_nano/_pymmcore_nano.cpython-311-darwin.so
pymmcore_nano/_pymmcore_nano.pyi
pymmcore_nano/py.typed
