Metadata-Version: 2.1
Name: pymmcore-nano
Version: 11.10.0.74.0
Summary: Alternative python bindings for MMCore, Micro-Manager's device control layer
Author: Micro-Manager Team
Author-Email: Mark Tsuchida <marktsuchida@gmail.com>, Talley Lambert <talley.lambert@gmail.com>
License: LGPL-2.1-only
Classifier: Development Status :: 4 - Beta
Classifier: License :: OSI Approved :: BSD License
Classifier: Programming Language :: Python :: 3
Classifier: Programming Language :: Python :: 3.9
Classifier: Programming Language :: Python :: 3.10
Classifier: Programming Language :: Python :: 3.11
Classifier: Programming Language :: Python :: 3.12
Classifier: Programming Language :: Python :: 3.13
Classifier: Typing :: Typed
Requires-Python: >=3.9
Requires-Dist: numpy>=1.25
Provides-Extra: test-devices
Requires-Dist: mm-test-adapters~=74.0; extra == "test-devices"
